README.rst
setup.cfg
setup.py
nbd/__init__.py
nbd/command.py
nbd/const.py
nbd/diff.py
nbd/export.py
nbd/fileops.py
nbd/git.py
nbd/main.py
nbd.egg-info/PKG-INFO
nbd.egg-info/SOURCES.txt
nbd.egg-info/dependency_links.txt
nbd.egg-info/entry_points.txt
nbd.egg-info/requires.txt
nbd.egg-info/top_level.txt
nbd/tests/__init__.py
nbd/tests/context.py
nbd/tests/test_diff.py
nbd/tests/test_export.py
nbd/tests/test_git.py
nbd/tests/test_main.py
nbd/tests/util.py