Metadata-Version: 1.1
Name: nbd
Version: 0.1.dev10
Summary: Lightweight ipython/jupyter notebook diffing tool
Home-page: https://github.com/lcary/nbd
Author: Luc Cary
Author-email: luc.cary@gmail.com
License: MIT
Download-URL: https://github.com/lcary/nbd/archive/v0.1.dev10.tar.gz
Keywords: ipynb jupyter ipython nbconvert git diff git-diff difftool
Platform: UNKNOWN
Classifier: Development Status :: 3 - Alpha
Classifier: Intended Audience :: Developers
Classifier: Topic :: Software Development :: Build Tools
Classifier: License :: OSI Approved :: MIT License
Classifier: Programming Language :: Python :: 2
Classifier: Programming Language :: Python :: 2.7
Classifier: Programming Language :: Python :: 3
Classifier: Programming Language :: Python :: 3.6
